jh_pymatgen/__init__.py
jh_pymatgen/cp2k_script_generator.py
jh_pymatgen/structure_process.py
jh_pymatgen-0.1.0.dist-info/METADATA
jh_pymatgen-0.1.0.dist-info/WHEEL
jh_pymatgen-0.1.0.dist-info/top_level.txt
jh_pymatgen-0.1.0.dist-info/RECORD
